taksonomia/__init__.py
taksonomia/__main__.py
taksonomia/anglify.py
taksonomia/cli.py
taksonomia/machine.py
taksonomia/taksonomia.py
taksonomia-2023.6.18.dist-info/LICENSE
taksonomia-2023.6.18.dist-info/METADATA
taksonomia-2023.6.18.dist-info/WHEEL
taksonomia-2023.6.18.dist-info/entry_points.txt
taksonomia-2023.6.18.dist-info/top_level.txt
taksonomia-2023.6.18.dist-info/RECORD
