Metadata-Version: 2.1
Name: taksonomia
Version: 2023.6.18
Summary: Taxonomy (Finnish: taksonomia) of a folder tree, guided by conventions.
Author-email: Stefan Hagen <stefan@hagen.link>
Maintainer-email: Stefan Hagen <stefan@hagen.link>
Project-URL: Homepage, https://git.sr.ht/~sthagen/taksonomia
Project-URL: Bug-Tracker, https://todo.sr.ht/~sthagen/taksonomia
Project-URL: Documentation, https://codes.dilettant.life/docs/taksonomia
Project-URL: Source-Code, https://git.sr.ht/~sthagen/taksonomia
Project-URL: Test-Coverage, https://codes.dilettant.life/coverage/taksonomia
Keywords: developer-tools,fingerprints,validation,verification,sbom,taxonomy
Classifier: Development Status :: 3 - Alpha
Classifier: Intended Audience :: Developers
Classifier: License :: OSI Approved :: MIT License
Classifier: Programming Language :: Python :: 3.10
Classifier: Programming Language :: Python :: 3.11
Classifier: Programming Language :: Python :: 3.12
Classifier: Programming Language :: Python :: 3.9
Requires-Python: >=3.9
License-File: LICENSE
Requires-Dist: PyYAML (>=6.0)
Requires-Dist: lxml (>=4.9.2)
Requires-Dist: msgspec (>=0.16.0)
Requires-Dist: psutil (>=5.9.5)
Requires-Dist: py-cpuinfo (>=9.0.0)
Provides-Extra: dev
Requires-Dist: black ; extra == 'dev'
Requires-Dist: coverage ; extra == 'dev'
Requires-Dist: hypothesis ; extra == 'dev'
Requires-Dist: mypy ; extra == 'dev'
Requires-Dist: pytest ; extra == 'dev'
Requires-Dist: pytest-cov ; extra == 'dev'
Requires-Dist: pytest-flake8 ; extra == 'dev'
Requires-Dist: types-jmespath ; extra == 'dev'
Requires-Dist: ruff ; extra == 'dev'
